CHANGES.rst
DESCRIPTION.rst
LICENSE
MANIFEST.in
README.md
setup.py
src/idc/imgvis/__init__.py
src/idc/imgvis/class_lister.py
src/idc/imgvis/filter/__init__.py
src/idc/imgvis/filter/_annotation_overlay_ic.py
src/idc/imgvis/filter/_annotation_overlay_is.py
src/idc/imgvis/filter/_annotation_overlay_od.py
src/idc/imgvis/filter/_center_overlay_od.py
src/idc/imgvis/filter/_combine_annotations.py
src/idc/imgvis/writer/__init__.py
src/idc/imgvis/writer/_annotation_overlay.py
src/idc/imgvis/writer/_image_viewer.py
src/image_dataset_converter_imgvis.egg-info/PKG-INFO
src/image_dataset_converter_imgvis.egg-info/SOURCES.txt
src/image_dataset_converter_imgvis.egg-info/dependency_links.txt
src/image_dataset_converter_imgvis.egg-info/entry_points.txt
src/image_dataset_converter_imgvis.egg-info/requires.txt
src/image_dataset_converter_imgvis.egg-info/top_level.txt